MANIFEST.in
README.md
README.rst
setup.cfg
setup.py
NanoStat.egg-info/PKG-INFO
NanoStat.egg-info/SOURCES.txt
NanoStat.egg-info/dependency_links.txt
NanoStat.egg-info/entry_points.txt
NanoStat.egg-info/requires.txt
NanoStat.egg-info/top_level.txt
nanostat/NanoStat.py
nanostat/__init__.py
nanostat/version.py
scripts/test.sh