Metadata-Version: 2.1
Name: NanoStat
Version: 1.5.0
Summary: Calculate statistics for Oxford Nanopore sequencing data and alignments
Home-page: https://github.com/wdecoster/nanostat
Author: Wouter De Coster
Author-email: decosterwouter@gmail.com
License: GPLv3
Keywords: nanopore sequencing statistics
Platform: UNKNOWN
Classifier: Development Status :: 4 - Beta
Classifier: Intended Audience :: Science/Research
Classifier: Topic :: Scientific/Engineering :: Bio-Informatics
Classifier: License :: OSI Approved :: MIT License
Classifier: Programming Language :: Python :: 3
Classifier: Programming Language :: Python :: 3.3
Classifier: Programming Language :: Python :: 3.4
Classifier: Programming Language :: Python :: 3.5
Requires-Python: >=3
